mapping/__init__.py
mapping/map_to_pymol.py
plotting/__init__.py
plotting/plotting.py
pwes-0.1.4.dist-info/LICENSE
pwes-0.1.4.dist-info/METADATA
pwes-0.1.4.dist-info/WHEEL
pwes-0.1.4.dist-info/top_level.txt
pwes-0.1.4.dist-info/RECORD
