Metadata-Version: 2.1
Name: pwes
Version: 0.1.4
Summary: A brief description of your package
License-File: LICENSE
Requires-Dist: pandas
Requires-Dist: scikit-learn
Requires-Dist: seaborn
Requires-Dist: matplotlib
Requires-Dist: scipy
Requires-Dist: numpy
Requires-Dist: biopython
